aboutcode/__init__.py
aboutcode/federatedcode/CHANGELOG.rst
aboutcode/federatedcode/README.rst
aboutcode/federatedcode/__init__.py
aboutcode/federatedcode/cli.py
aboutcode/federatedcode/client/__init__.py
aboutcode/federatedcode/contrib/__init__.py
aboutcode/federatedcode/contrib/django/__init__.py
aboutcode/federatedcode/contrib/django/models.py
aboutcode/federatedcode/contrib/django/utils.py
aboutcode_federatedcode-0.1.0.dist-info/entry_points.txt
aboutcode_federatedcode-0.1.0.dist-info/WHEEL
aboutcode_federatedcode-0.1.0.dist-info/METADATA
aboutcode_federatedcode-0.1.0.dist-info/NOTICE
aboutcode_federatedcode-0.1.0.dist-info/apache-2.0.LICENSE
aboutcode_federatedcode-0.1.0.dist-info/RECORD
