Metadata-Version: 2.1
Name: aboutcode.federatedcode
Version: 0.1.0
Summary: A library for FederatedCode client
Keywords: purl,Package-URL,open source,package,sca,scan,activitypub,dependencies
Author-email: "AboutCode, nexB Inc. and others" <info@aboutcode.org>
Requires-Python: >=3.9
Classifier: Development Status :: 5 - Production/Stable
Classifier: Intended Audience :: Developers
Classifier: Programming Language :: Python :: 3
Classifier: Programming Language :: Python :: 3 :: Only
Classifier: Topic :: Software Development
Classifier: Topic :: Utilities
Requires-Dist: aboutcode.hashid>=0.2.0
Requires-Dist: click>=8.1.7
Requires-Dist: Django>=5.1.2
Requires-Dist: packageurl_python >= 0.16.0
Requires-Dist: python-dotenv>=1.0.1
Requires-Dist: requests>=2.32.3
Requires-Dist: saneyaml>=0.6.0
Project-URL: Homepage, https://github.com/aboutcode-org/federatedcode
